ked/__init__.py
ked/__main__.py
ked/about.py
ked/bindings.py
ked/cli.py
ked/config.py
ked/dialogs.py
ked/editor.py
ked/help.py
ked/meta.py
ked/palette.py
ked/settings.py
ked/settings.yaml
ked/statusbar.py
ked/styles.tcss
ked/tui.py
ked/widgets.py
ked-0.6.2.dist-info/licenses/license.txt
ked-0.6.2.dist-info/WHEEL
ked-0.6.2.dist-info/entry_points.txt
ked-0.6.2.dist-info/METADATA
ked-0.6.2.dist-info/RECORD
