Metadata-Version: 2.4
Name: Ked
Version: 0.6.2
Summary: simple text editor for the terminal
Keywords: editor,terminal
Author: John Hennig
License-Expression: CC-BY-NC-ND-4.0
License-File: license.txt
Classifier: Development Status :: 3 - Alpha
Classifier: Operating System :: OS Independent
Classifier: Topic :: Text Editors
Requires-Dist: textual[syntax]>=6
Requires-Dist: rich>=14
Requires-Dist: cyclopts>=4
Requires-Dist: pyyaml>=6
Requires-Python: >=3.11
Project-URL: Source, https://github.com/john-hen/Ked
Project-URL: Releases, https://github.com/john-hen/Ked/releases
